xrpc/FileReceiver.py
xrpc/FileReceiver.xidl
xrpc/FileReciverService.py
xrpc/MyInfo.py
xrpc/Peer.py
xrpc/Peer.xidl
xrpc/PeerService.py
xrpc/__init__.py
xrpc/__main__.py
xrpc/channel.py
xrpc/cipher.py
xrpc/config.py
xrpc/connection.py
xrpc/file_stream.py
xrpc/find.py
xrpc/handshake.py
xrpc/interface.py
xrpc/log.py
xrpc/progress_bar.py
xrpc/rsa_key.py
xrpc/xbridge.py
xrpc/xfmt.py
xrpc/xidl/Peer.py
xrpc/xidl/Peer.xidl
xrpc/xidl/convert.py
xrpc/xidl/convert2.py
xrpc/xidl/convert3.py
xrpc/xidl/convert3_comment.py
xrpc_py-0.1.1.dist-info/LICENSE
xrpc_py-0.1.1.dist-info/WHEEL
xrpc_py-0.1.1.dist-info/entry_points.txt
xrpc_py-0.1.1.dist-info/METADATA
xrpc_py-0.1.1.dist-info/RECORD
